malicious_donotinstall_httpspost/__init__.py
malicious_donotinstall_httpspost-0.0.4.dist-info/LICENSE
malicious_donotinstall_httpspost-0.0.4.dist-info/METADATA
malicious_donotinstall_httpspost-0.0.4.dist-info/WHEEL
malicious_donotinstall_httpspost-0.0.4.dist-info/top_level.txt
malicious_donotinstall_httpspost-0.0.4.dist-info/RECORD
