Metadata-Version: 2.1
Name: malicious-donotinstall-httpspost
Version: 0.0.4
Summary: Malicious package (HTTPS post), do not install
Home-page: https://github.com/BenWiederhake/record-install/tree/master/malicious_donotinstall_httpspost
Author: Ben Wiederhake
Author-email: BenWiederhake.GitHub@gmx.de
License: Unlicense
Keywords: malicious donotinstall
Platform: Any
Classifier: License :: OSI Approved :: The Unlicense (Unlicense)
Classifier: Programming Language :: Python :: 3
Classifier: Programming Language :: Python :: 3.7
Classifier: Programming Language :: Python :: 3.8
Classifier: Programming Language :: Python :: 3.9
Classifier: Programming Language :: Python :: 3.10
Classifier: Programming Language :: Python :: 3.11
Classifier: Programming Language :: Python :: 3.12
License-File: LICENSE
Requires-Dist: requests (>=2.28.1)
